robot_kpi_metrics/__init__.py
robot_kpi_metrics/dashboard_stats.py
robot_kpi_metrics/details.py
robot_kpi_metrics/keyword_results.py
robot_kpi_metrics/keyword_times.py
robot_kpi_metrics/robotmetrics.py
robot_kpi_metrics/runner.py
robot_kpi_metrics/suite_results.py
robot_kpi_metrics/test_results.py
robot_kpi_metrics/version.py
robot_kpi_metrics/templates/index.html
robot_kpi_metrics-1.0.0.dist-info/licenses/LICENSE
robot_kpi_metrics-1.0.0.dist-info/METADATA
robot_kpi_metrics-1.0.0.dist-info/WHEEL
robot_kpi_metrics-1.0.0.dist-info/entry_points.txt
robot_kpi_metrics-1.0.0.dist-info/top_level.txt
robot_kpi_metrics-1.0.0.dist-info/RECORD
