Metadata-Version: 2.4
Name: robot-kpi-metrics
Version: 1.0.0
Summary: Custom KPI report for robot framework
Home-page: https://github.com/mrlaw74/robot-kpi-metrics
Author: Your Name
Author-email: nvluathcmut@gmail.com
License: MIT
Keywords: robotframework report kpi metrics
Classifier: Framework :: Robot Framework
Classifier: Programming Language :: Python
Classifier: Topic :: Software Development :: Testing
License-File: LICENSE
Requires-Dist: robotframework
Requires-Dist: jinja2
Requires-Dist: pandas
Dynamic: author
Dynamic: author-email
Dynamic: classifier
Dynamic: description
Dynamic: home-page
Dynamic: keywords
Dynamic: license
Dynamic: license-file
Dynamic: requires-dist
Dynamic: summary
